{"cameraMode":{"drawMode":0,"name":"Shaded","section":"Shading Mode"},"sceneLighting":true,"audioPlay":false,"sceneViewState":{"showFog":true,"showMaterialUpdate":false,"showSkybox":true,"showFlares":true,"showImageEffects":true,"showParticleSystems":true},"in2DMode":false,"pivot":{"x":-2056.78125,"y":-516.3809814453125,"z":-1386.0245361328125},"rotation":{"x":0.4298561215400696,"y":-0.14685720205307008,"z":0.07108583301305771,"w":0.8880335092544556},"size":3262.96240234375,"orthographic":false}